deephaven/DeephavenDb.py
deephaven/__init__.py
deephaven/conversion_utils.py
deephaven/java_to_python.py
deephaven/jvm_init.py
deephaven/python_to_java.py
deephaven/start_jvm.py
deephaven/Calendars/__init__.py
deephaven/ComboAggregateFactory/__init__.py
deephaven/DBTimeUtils/__init__.py
deephaven/ExportTools/JdbcLogger.py
deephaven/ExportTools/__init__.py
deephaven/ImportTools/CsvImport.py
deephaven/ImportTools/DownsampleImport.py
deephaven/ImportTools/JdbcHelpers.py
deephaven/ImportTools/JdbcImport.py
deephaven/ImportTools/JsonImport.py
deephaven/ImportTools/MergeData.py
deephaven/ImportTools/XmlImport.py
deephaven/ImportTools/__init__.py
deephaven/InputTableTools/InputTable.py
deephaven/InputTableTools/TableInputHandler.py
deephaven/InputTableTools/__init__.py
deephaven/MovingAverages/__init__.py
deephaven/Parallel/ParallelQueryExecution.py
deephaven/Parallel/__init__.py
deephaven/PerformanceTools/__init__.py
deephaven/Plot/__init__.py
deephaven/Plot/figure_wrapper.py
deephaven/Plot/ColorMaps/__init__.py
deephaven/QueryScope/__init__.py
deephaven/TableManagementTools/__init__.py
deephaven/TableManipulation/PersistentQueryTableHelper.py
deephaven/TableManipulation/WindowCheck.py
deephaven/TableManipulation/_PersistentQueryControllerClient.py
deephaven/TableManipulation/__init__.py
deephaven/TableTools/__init__.py
deephaven/UpdateBy/EmaControl.py
deephaven/UpdateBy/__init__.py
deephaven/lang/ListBasedSet.py
deephaven/lang/__init__.py
deephaven/lang/analyzer.py
deephaven/lang/arrays.py
deephaven/lang/constants.py
deephaven/lang/tools.py
deephaven/lang/transformer.py
deephaven/lang/vectorize_simple.py
deephaven/npy/__init__.py
deephaven/npy/table2numpy.py
test/lang/__init__.py
test/lang/benchmark.py
test/lang/playground.py
test/lang/playground_cuda.py
deephaven-1.20221001.62.dist-info/LICENSE.txt
deephaven-1.20221001.62.dist-info/METADATA
deephaven-1.20221001.62.dist-info/WHEEL
deephaven-1.20221001.62.dist-info/top_level.txt
deephaven-1.20221001.62.dist-info/RECORD
