Metadata-Version: 2.1
Name: deephaven
Version: 1.20221001.62
Summary: Python integrations for Deephaven
Home-page: https://www.deephaven.io/
Author: Deephaven Data Labs
Author-email: python@deephaven.io
License: Apache 2.0
Keywords: Deephaven Development
Classifier: Development Status :: 3 - Alpha
Classifier: Intended Audience :: Developers
Classifier: Topic :: Software Development :: Build Tools
Classifier: License :: OSI Approved :: Apache Software License
Classifier: Programming Language :: Python :: 2.7
Classifier: Programming Language :: Python :: 3.6
Classifier: Programming Language :: Python :: 3.7
License-File: LICENSE.txt
Requires-Dist: jpy (==0.11.0)
Requires-Dist: numpy
Requires-Dist: dill (>=0.2.8)
Requires-Dist: wrapt
Requires-Dist: pandas
Requires-Dist: enum34 ; python_version < "3.4"
Requires-Dist: numba ; python_version > "3.0"
